gguf_pack/__init__.py
gguf_pack/__main__.py
gguf_pack-0.0.32.dist-info/LICENSE
gguf_pack-0.0.32.dist-info/WHEEL
gguf_pack-0.0.32.dist-info/METADATA
gguf_pack-0.0.32.dist-info/RECORD
