Metadata-Version: 2.1
Name: gguf-pack
Version: 0.0.32
Summary: gguf portable pack for picture/audio/video generation
Author-email: calcuis <info@calcu.io>
Classifier: License :: OSI Approved :: MIT License
Requires-Dist: tqdm
Project-URL: Download, https://github.com/calcuis/gguf-pack/releases
Project-URL: GitHub, https://github.com/calcuis/gguf-pack
Project-URL: Homepage, https://gguf.org
